AeroViz/__init__.py
AeroViz/mcp_server.py
AeroViz/__pycache__/__init__.cpython-312.pyc
AeroViz/data/DEFAULT_DATA.csv
AeroViz/data/DEFAULT_PNSD_DATA.csv
AeroViz/data/hysplit_example_data.txt
AeroViz/dataProcess/README.md
AeroViz/dataProcess/__init__.py
AeroViz/dataProcess/Chemistry/__init__.py
AeroViz/dataProcess/Chemistry/_calculate.py
AeroViz/dataProcess/Chemistry/_isoropia.py
AeroViz/dataProcess/Chemistry/_mass_volume.py
AeroViz/dataProcess/Chemistry/_ocec.py
AeroViz/dataProcess/Chemistry/isrpia.cnf
AeroViz/dataProcess/Chemistry/isrpia2.exe
AeroViz/dataProcess/Chemistry/__pycache__/__init__.cpython-312.pyc
AeroViz/dataProcess/Optical/PyMieScatt_update.py
AeroViz/dataProcess/Optical/_IMPROVE.py
AeroViz/dataProcess/Optical/__init__.py
AeroViz/dataProcess/Optical/_derived.py
AeroViz/dataProcess/Optical/_extinction.py
AeroViz/dataProcess/Optical/_mie_sd.py
AeroViz/dataProcess/Optical/_retrieve_RI.py
AeroViz/dataProcess/Optical/coefficient.py
AeroViz/dataProcess/Optical/fRH.pkl
AeroViz/dataProcess/Optical/mie_theory.py
AeroViz/dataProcess/Optical/__pycache__/PyMieScatt_update.cpython-312.pyc
AeroViz/dataProcess/Optical/__pycache__/__init__.cpython-312.pyc
AeroViz/dataProcess/Optical/__pycache__/mie_theory.cpython-312.pyc
AeroViz/dataProcess/SizeDistr/__init__.py
AeroViz/dataProcess/SizeDistr/_size_dist.py
AeroViz/dataProcess/SizeDistr/prop.py
AeroViz/dataProcess/SizeDistr/__pycache__/__init__.cpython-312.pyc
AeroViz/dataProcess/SizeDistr/__pycache__/_size_dist.cpython-312.pyc
AeroViz/dataProcess/SizeDistr/merge/README.md
AeroViz/dataProcess/SizeDistr/merge/__init__.py
AeroViz/dataProcess/SizeDistr/merge/_merge_v0.py
AeroViz/dataProcess/SizeDistr/merge/_merge_v0_1.py
AeroViz/dataProcess/SizeDistr/merge/_merge_v1.py
AeroViz/dataProcess/SizeDistr/merge/_merge_v2.py
AeroViz/dataProcess/SizeDistr/merge/_merge_v3.py
AeroViz/dataProcess/SizeDistr/merge/_merge_v4.py
AeroViz/dataProcess/VOC/__init__.py
AeroViz/dataProcess/VOC/_potential_par.py
aeroviz-0.1.24.dist-info/licenses/LICENSE
aeroviz-0.1.24.dist-info/METADATA
aeroviz-0.1.24.dist-info/WHEEL
aeroviz-0.1.24.dist-info/top_level.txt
aeroviz-0.1.24.dist-info/RECORD
