Metadata-Version: 2.4
Name: AeroViz
Version: 0.1.24
Summary: Aerosol data processing and visualization toolkit. Read, QC, and analyze data from SMPS, APS, AE33, TEOM, Nephelometer, XRF, and 15+ atmospheric instruments.
Author-email: Alex Chan <alex870521@gmail.com>
License: MIT
Project-URL: Homepage, https://github.com/Alex870521/AeroViz
Project-URL: Documentation, https://alex870521.github.io/AeroViz/
Project-URL: Repository, https://github.com/Alex870521/AeroViz
Project-URL: Issues, https://github.com/Alex870521/AeroViz/issues
Project-URL: Changelog, https://github.com/Alex870521/AeroViz/blob/main/docs/CHANGELOG.md
Keywords: aerosol,atmospheric-science,air-quality,data-processing,visualization,PM2.5,PM10,black-carbon,particle-size-distribution,optical-properties,SMPS,APS,aethalometer,nephelometer,TEOM,XRF,OC-EC,environmental-monitoring,research,quality-control
Classifier: Development Status :: 4 - Beta
Classifier: Intended Audience :: Science/Research
Classifier: Intended Audience :: Developers
Classifier: Topic :: Scientific/Engineering :: Atmospheric Science
Classifier: Topic :: Scientific/Engineering :: Visualization
Classifier: Topic :: Scientific/Engineering :: Chemistry
Classifier: Programming Language :: Python :: 3
Classifier: Programming Language :: Python :: 3.10
Classifier: Programming Language :: Python :: 3.11
Classifier: Programming Language :: Python :: 3.12
Classifier: Programming Language :: Python :: 3.13
Classifier: License :: OSI Approved :: MIT License
Classifier: Operating System :: OS Independent
Requires-Python: >=3.10
License-File: LICENSE
Requires-Dist: pandas>=2.2.0
Requires-Dist: numpy>=2.0.0
Requires-Dist: matplotlib>=3.8.4
Requires-Dist: scipy>=1.15.0
Requires-Dist: seaborn>=0.13.2
Requires-Dist: scikit-learn>=1.5.1
Requires-Dist: windrose>=1.9.2
Requires-Dist: cartopy>=0.24.1
Requires-Dist: tabulate>=0.9.0
Requires-Dist: rich~=13.9.4
Requires-Dist: numba>=0.63.0
Provides-Extra: test
Requires-Dist: pytest>=7.0.0; extra == "test"
Requires-Dist: pytest-cov>=4.1.0; extra == "test"
Requires-Dist: pytest-mock>=3.10.0; extra == "test"
Provides-Extra: dev
Requires-Dist: black>=23.0; extra == "dev"
Requires-Dist: isort>=5.12.0; extra == "dev"
Requires-Dist: flake8>=6.0.0; extra == "dev"
Requires-Dist: mypy>=1.5.0; extra == "dev"
Requires-Dist: build; extra == "dev"
Requires-Dist: twine; extra == "dev"
Provides-Extra: docs
Requires-Dist: mkdocs>=1.4.0; extra == "docs"
Requires-Dist: mkdocs-material>=8.0; extra == "docs"
Requires-Dist: mkdocstrings[python]>=0.18.0; extra == "docs"
Dynamic: license-file
